nat/meta/pypi.md
nat/plugins/adk/__init__.py
nat/plugins/adk/adk_callback_handler.py
nat/plugins/adk/llm.py
nat/plugins/adk/register.py
nat/plugins/adk/tool_wrapper.py
nvidia_nat_adk-1.3.1.dist-info/licenses/LICENSE-3rd-party.txt
nvidia_nat_adk-1.3.1.dist-info/licenses/LICENSE.md
nvidia_nat_adk-1.3.1.dist-info/METADATA
nvidia_nat_adk-1.3.1.dist-info/WHEEL
nvidia_nat_adk-1.3.1.dist-info/entry_points.txt
nvidia_nat_adk-1.3.1.dist-info/top_level.txt
nvidia_nat_adk-1.3.1.dist-info/RECORD
